cyclonedx_buildroot/__init__.py
cyclonedx_buildroot/__main__.py
cyclonedx_buildroot/_internal/__init__.py
cyclonedx_buildroot/_internal/cli.py
cyclonedx_buildroot/py.typed
cyclonedx_buildroot-2.0.0.dist-info/LICENSE
cyclonedx_buildroot-2.0.0.dist-info/METADATA
cyclonedx_buildroot-2.0.0.dist-info/WHEEL
cyclonedx_buildroot-2.0.0.dist-info/entry_points.txt
cyclonedx_buildroot-2.0.0.dist-info/RECORD
