Metadata-Version: 2.3
Name: CycloneDX-Buildroot
Version: 2.0.0
Summary: Create a software bill of materials from the direct dependencies of a Buildroot generated project
License: Apache-2.0
Keywords: OWASP,CycloneDX,bill-of-materials,BOM,software-bill-of-materials,SBOM,environment,virtualenv,venv,Poetry,Pipenv,requirements,PDM,Conda,SPDX,licenses,PURL,package-url,dependency-graph,buildroot
Author: Robert Smigielski
Author-email: ptdropper@gmail.com
Maintainer: Robert Smigielski
Maintainer-email: ptdropper@gmail.com
Requires-Python: >=3.8,<4.0
Classifier: Development Status :: 5 - Production/Stable
Classifier: Environment :: Console
Classifier: Intended Audience :: Developers
Classifier: Intended Audience :: Information Technology
Classifier: Intended Audience :: Legal Industry
Classifier: Intended Audience :: System Administrators
Classifier: License :: OSI Approved :: Apache Software License
Classifier: Programming Language :: Python :: 3
Classifier: Programming Language :: Python :: 3.8
Classifier: Programming Language :: Python :: 3.9
Classifier: Programming Language :: Python :: 3.10
Classifier: Programming Language :: Python :: 3.11
Classifier: Programming Language :: Python :: 3.12
Classifier: Programming Language :: Python :: 3.13
Classifier: Topic :: Security
Classifier: Topic :: Software Development
Classifier: Topic :: System :: Software Distribution
Classifier: Typing :: Typed
Requires-Dist: cyclonedx-python-lib (>=8.5.0,<9.0.0)
Requires-Dist: packageurl-python (>=0.16,<2)
Project-URL: Bug Tracker, https://github.com/CycloneDX/cyclonedx-buildroot/issues
Project-URL: Funding, https://owasp.org/donate/?reponame=www-project-cyclonedx&title=OWASP+CycloneDX
Project-URL: Homepage, https://github.com/CycloneDX/cyclonedx-buildroot/#readme
Project-URL: Repository, https://github.com/CycloneDX/cyclonedx-buildroot/
